{
    "version": "0.7.4",
    "architecture": {
        "64bit": {
            "url": "https://github.com/aretw0/trellis/releases/download/v0.7.4/trellis_Windows_x86_64.zip",
            "bin": [
                "trellis.exe"
            ],
            "hash": "0dc1a4f3bd90f85435c11bd696be95255723bb3efe86c7846fa40543150fd70b"
        },
        "arm64": {
            "url": "https://github.com/aretw0/trellis/releases/download/v0.7.4/trellis_Windows_arm64.zip",
            "bin": [
                "trellis.exe"
            ],
            "hash": "b4d5e4054621d5a161a1fd3c945bbd2a6dfa1d77f0be456e18cef023cc8db841"
        }
    },
    "homepage": "https://github.com/aretw0/trellis",
    "license": "AGPL-3.0",
    "description": "Deterministic state machine engine for CLIs and automation."
}
